README.md
pytest_custom_concurrency.py
setup.py
pytest_custom_concurrency.egg-info/PKG-INFO
pytest_custom_concurrency.egg-info/SOURCES.txt
pytest_custom_concurrency.egg-info/dependency_links.txt
pytest_custom_concurrency.egg-info/entry_points.txt
pytest_custom_concurrency.egg-info/requires.txt
pytest_custom_concurrency.egg-info/top_level.txt
test/test_plugin.py